nonebot_plugin_mysticism/__init__.py
nonebot_plugin_mysticism/config.py
nonebot_plugin_mysticism/rule.py
nonebot_plugin_mysticism/tarot.py
nonebot_plugin_mysticism/tarot_dict/__init__.py
nonebot_plugin_mysticism/tarot_dict/tarot_formations.yaml
nonebot_plugin_mysticism/tarot_dict/tarot_keywords.yml
nonebot_plugin_mysticism/tarot_theme/__init__.py
nonebot_plugin_mysticism/tarot_theme/bilibili.yaml
nonebot_plugin_mysticism/tarot_theme/blue_archive.yaml
nonebot_plugin_mysticism/tarot_theme/waite.yaml
nonebot_plugin_mysticism/tarot_uitls.py
nonebot_plugin_mysticism-0.1.6.dist-info/LICENSE
nonebot_plugin_mysticism-0.1.6.dist-info/METADATA
nonebot_plugin_mysticism-0.1.6.dist-info/WHEEL
nonebot_plugin_mysticism-0.1.6.dist-info/RECORD
