Metadata-Version: 2.1
Name: nonebot-plugin-mysticism
Version: 0.1.6
Summary: 占卜辅助工具
Home-page: https://github.com/Yan-Zero/nonebot_plugin_mysticism
License: Apache-2.0
Keywords: tarot,nonebot,nonebot2,bot,qq
Author: Yan
Author-email: 1964649083@qq.com
Requires-Python: >=3.11,<4.0
Classifier: License :: OSI Approved :: Apache Software License
Classifier: Programming Language :: Python :: 3
Classifier: Programming Language :: Python :: 3.11
Classifier: Programming Language :: Python :: 3.12
Requires-Dist: aiohttp (>=3.9.5,<4.0.0)
Requires-Dist: nonebot-adapter-onebot (>=2.4.3,<3.0.0)
Requires-Dist: nonebot2 (>=2.3.0,<3.0.0)
Requires-Dist: pillow (>=10.3.0,<11.0.0)
Requires-Dist: pyyaml (>=6.0.1,<7.0.0)
